sshclient/__init__.py
sshclient/sshclient.py
sshclient_malbizer-1.0.0.data/scripts/sshclient-send.py
sshclient_malbizer-1.0.0.dist-info/METADATA
sshclient_malbizer-1.0.0.dist-info/WHEEL
sshclient_malbizer-1.0.0.dist-info/top_level.txt
sshclient_malbizer-1.0.0.dist-info/RECORD
