Metadata-Version: 2.1
Name: sshclient-malbizer
Version: 1.0.0
Summary: Pacote SSH para EC2
Home-page: UNKNOWN
Author: Anderson Souza
Author-email: anderson@malbizer.com.br
License: UNKNOWN
Keywords: python,ssh,clientssh,ec2
Platform: UNKNOWN
Classifier: Development Status :: 3 - Alpha
Classifier: Intended Audience :: Education
Classifier: Programming Language :: Python :: 2
Classifier: Programming Language :: Python :: 3
Classifier: Operating System :: MacOS :: MacOS X
Classifier: Operating System :: Microsoft :: Windows
Requires-Dist: paramiko (==2.9.2)
Requires-Dist: six (==1.16.0)
